setup.py
keepalive/__init__.py
keepalive/keepalive.py
keepalive.egg-info/PKG-INFO
keepalive.egg-info/SOURCES.txt
keepalive.egg-info/dependency_links.txt
keepalive.egg-info/top_level.txt