Metadata-Version: 1.1
Name: keepalive
Version: 0.4.1
Summary: urllib keepalive support for python
Home-page: https://github.com/wikier/keepalive
Author: Sergio Fernández
Author-email: sergio@wikier.org
License: GNU GPL
Download-URL: https://github.com/wikier/keepalive/releases
Keywords: python http urllib keepalive
Platform: any
Classifier: Development Status :: 4 - Beta
Classifier: Intended Audience :: Developers
Classifier: License :: OSI Approved :: Apache Software License
Classifier: Operating System :: OS Independent
Classifier: Programming Language :: Python :: 2
Classifier: Programming Language :: Python :: 3
